panda3d_toolbox/__init__.py
panda3d_toolbox/__version__.py
panda3d_toolbox/bootstrap.py
panda3d_toolbox/prc.py
panda3d_toolbox/registry.py
panda3d_toolbox/runtime.py
panda3d_toolbox/singleton.py
panda3d_toolbox/utils.py
panda3d_toolbox-1.1.0.dist-info/LICENSE
panda3d_toolbox-1.1.0.dist-info/METADATA
panda3d_toolbox-1.1.0.dist-info/WHEEL
panda3d_toolbox-1.1.0.dist-info/top_level.txt
panda3d_toolbox-1.1.0.dist-info/RECORD
